<Properties StartupConfiguration="{21DA60DD-9681-47DF-8799-351ED9AF9812}|Default">
  <MonoDevelop.Ide.ItemProperties.CalendarCarouselView.Android TriggeredFromHotReload="False" PreferredExecutionTarget="Android.pixel_2_pie_9_0_-_api_28" />
  <MonoDevelop.Ide.Workbench ActiveDocument="CalendarCarouselView/MainPage.xaml.cs">
    <Files>
      <File FileName="CalendarCarouselView/CellStackLayout.cs" Line="1" Column="1" />
      <File FileName="CalendarCarouselView/MainPage.xaml.cs" Line="1" Column="1" />
    </Files>
    <Pads>
      <Pad Id="ProjectPad">
        <State name="__root__">
          <Node name="CalendarCarouselView" expanded="True">
            <Node name="CalendarCarouselView" expanded="True">
              <Node name="MainPage.xaml" expanded="True">
                <Node name="MainPage.xaml.cs" selected="True" />
              </Node>
            </Node>
            <Node name="CalendarCarouselView.iOS" expanded="True" />
          </Node>
        </State>
      </Pad>
    </Pads>
  </MonoDevelop.Ide.Workbench>
  <MonoDevelop.Ide.ItemProperties.CalendarCarouselView.iOS TriggeredFromHotReload="False" PreferredExecutionTarget="MonoDevelop.IPhone.IPhoneSimulatorTarget.0431F661-E1F4-4ABD-B88B-50D5EFCDEBD6" />
  <MonoDevelop.Ide.DebuggingService.PinnedWatches />
  <MonoDevelop.Ide.Workspace ActiveConfiguration="Debug" />
  <MonoDevelop.Ide.DebuggingService.Breakpoints>
    <BreakpointStore />
  </MonoDevelop.Ide.DebuggingService.Breakpoints>
  <MultiItemStartupConfigurations />
</Properties>